{"data":{"_id":11000,"properties":{"animal":{"name":"animal","kind":"scalar","getter":false,"setter":false,"type":"string","array":false,"runtimeType":"string"},"imageUrl":{"name":"imageUrl","kind":"scalar","persist":false,"getter":false,"setter":false,"type":"string","default":"http://localhost:3005/public/animals/undefined.png","runtimeType":"string","array":false}},"primaryKeys":[],"filters":{},"hooks":{},"indexes":[],"uniques":[],"className":"Animal","path":"./src/domain/exercise/animalExercise/Entity.ts","name":"Animal","embeddable":true,"abstract":false,"internal":true,"constructorParams":["animal"],"toJsonParams":[],"useCache":true,"collection":"animal"},"origin":"./src/domain/exercise/animalExercise/Entity.ts","hash":"9c7a860da23c119fe3b1d73796d7b13e","version":"6.4.16"}
