{"data":{"_id":14000,"properties":{"colorChallenges":{"name":"colorChallenges","type":"ColorChallenge","kind":"embedded","array":true,"prefix":true,"object":true,"runtimeType":"Collection<ColorChallenge, object>"}},"primaryKeys":[],"filters":{},"hooks":{},"indexes":[],"uniques":[],"className":"ColorExercise","path":"./src/domain/exercise/colorExercise/Entity.ts","name":"ColorExercise","abstract":false,"internal":true,"constructorParams":["title","description","durationMinutes","mainColor","thumbnailUrl","ageRange","difficulty","xp","colorChallenges"],"toJsonParams":[],"extends":"Exercise","useCache":true,"collection":"color_exercise"},"origin":"./src/domain/exercise/colorExercise/Entity.ts","hash":"d32612e629621ca182edddf4bbf7d4f9","version":"6.4.16"}
